mcpscanner/__init__.py
mcpscanner/__main__.py
mcpscanner-0.3.0.dist-info/WHEEL
mcpscanner-0.3.0.dist-info/entry_points.txt
mcpscanner-0.3.0.dist-info/METADATA
mcpscanner-0.3.0.dist-info/RECORD
