Metadata-Version: 2.4
Name: mcpscanner
Version: 0.3.0
Summary: A command-line tool for analyzing MCP servers.
Author: Pangea
Author-email: Pangea <support@pangea.cloud>
License-Expression: MIT
Requires-Dist: cyclopts>=3.22.5
Requires-Dist: fastembed>=0.7.1
Requires-Dist: fastmcp>=2.11.0
Requires-Dist: mcp>=1.12.3
Requires-Dist: pangea-sdk>=6.4.0
Requires-Dist: pydantic>=2.11.7
Requires-Dist: pyjson5>=1.6.9
Requires-Dist: rich>=14.1.0
Requires-Dist: scipy>=1.16.1
Requires-Python: >=3.11
